{
    "asset": {
        "format": "jpg",
        "id": "ed667f58c5c7c7f3a6cb22f98846227f",
        "name": "images%20-%202020-04-17T123955.371.jpg",
        "path": "file:/Users/ankitkhandelwal/Documents/TrainYourOwnYOLO/Data/Source_Images/Training_Images/images%20-%202020-04-17T123955.371.jpg",
        "size": {
            "width": 290,
            "height": 174
        },
        "state": 2,
        "type": 1
    },
    "regions": [
        {
            "id": "tMp8lXfZ7",
            "type": "RECTANGLE",
            "tags": [
                "Mug"
            ],
            "boundingBox": {
                "height": 102.6834724378882,
                "width": 159.59601533457248,
                "left": 101.14036361524163,
                "top": 71.3165275621118
            },
            "points": [
                {
                    "x": 101.14036361524163,
                    "y": 71.3165275621118
                },
                {
                    "x": 260.7363789498141,
                    "y": 71.3165275621118
                },
                {
                    "x": 260.7363789498141,
                    "y": 174
                },
                {
                    "x": 101.14036361524163,
                    "y": 174
                }
            ]
        },
        {
            "id": "gzPAGHlX8",
            "type": "RECTANGLE",
            "tags": [
                "Mug"
            ],
            "boundingBox": {
                "height": 101.1214576863354,
                "width": 130.03339916356876,
                "left": 145.7790717936803,
                "top": 1.0807453416149069
            },
            "points": [
                {
                    "x": 145.7790717936803,
                    "y": 1.0807453416149069
                },
                {
                    "x": 275.81247095724905,
                    "y": 1.0807453416149069
                },
                {
                    "x": 275.81247095724905,
                    "y": 102.20220302795032
                },
                {
                    "x": 145.7790717936803,
                    "y": 102.20220302795032
                }
            ]
        },
        {
            "id": "46hul_bON",
            "type": "RECTANGLE",
            "tags": [
                "Mug"
            ],
            "boundingBox": {
                "height": 119.48990683229815,
                "width": 152.46224442379182,
                "left": 20.53801696096654,
                "top": 36.59758346273292
            },
            "points": [
                {
                    "x": 20.53801696096654,
                    "y": 36.59758346273292
                },
                {
                    "x": 173.00026138475835,
                    "y": 36.59758346273292
                },
                {
                    "x": 173.00026138475835,
                    "y": 156.08749029503107
                },
                {
                    "x": 20.53801696096654,
                    "y": 156.08749029503107
                }
            ]
        },
        {
            "id": "8gdd5OHpV",
            "type": "RECTANGLE",
            "tags": [
                "Mug"
            ],
            "boundingBox": {
                "height": 67.10753105590062,
                "width": 136.80921816914497,
                "left": 36.27105599442379,
                "top": 0.937208850931677
            },
            "points": [
                {
                    "x": 36.27105599442379,
                    "y": 0.937208850931677
                },
                {
                    "x": 173.08027416356876,
                    "y": 0.937208850931677
                },
                {
                    "x": 173.08027416356876,
                    "y": 68.0447399068323
                },
                {
                    "x": 36.27105599442379,
                    "y": 68.0447399068323
                }
            ]
        }
    ],
    "version": "2.1.0"
}